{"data": {"ACEH": {"cakupan_ratio": "70.23", "paslon_1_count": "1450698", "paslon_2_count": "412602", "paslon_3_count": "42344"}, "BALI": {"cakupan_ratio": "55.22", "paslon_1_count": "31704", "paslon_2_count": "521234", "paslon_3_count": "450005"}, "BANTEN": {"cakupan_ratio": "67.21", "paslon_1_count": "1284147", "paslon_2_count": "2152431", "paslon_3_count": "363483"}, "BENGKULU": {"cakupan_ratio": "87.78", "paslon_1_count": "201315", "paslon_2_count": "780178", "paslon_3_count": "128961"}, "DAERAH ISTIMEWA YOGYAKARTA": {"cakupan_ratio": "77.43", "paslon_1_count": "285293", "paslon_2_count": "762480", "paslon_3_count": "447780"}, "DKI JAKARTA": {"cakupan_ratio": "69.62", "paslon_1_count": "1442417", "paslon_2_count": "1474847", "paslon_3_count": "625564"}, "GORONTALO": {"cakupan_ratio": "82.74", "paslon_1_count": "152736", "paslon_2_count": "344440", "paslon_3_count": "28720"}, "JAMBI": {"cakupan_ratio": "74.61", "paslon_1_count": "371634", "paslon_2_count": "977863", "paslon_3_count": "158770"}, "JAWA BARAT": {"cakupan_ratio": "69.26", "paslon_1_count": "5353028", "paslon_2_count": "9679261", "paslon_3_count": "1629090"}, "JAWA TENGAH": {"cakupan_ratio": "87.46", "paslon_1_count": "2305139", "paslon_2_count": "9598377", "paslon_3_count": "6256840"}, "JAWA TIMUR": {"cakupan_ratio": "81.82", "paslon_1_count": "2533261", "paslon_2_count": "10691012", "paslon_3_count": "2829561"}, "KALIMANTAN BARAT": {"cakupan_ratio": "75.14", "paslon_1_count": "452993", "paslon_2_count": "1174594", "paslon_3_count": "314853"}, "KALIMANTAN SELATAN": {"cakupan_ratio": "64.85", "paslon_1_count": "462514", "paslon_2_count": "712320", "paslon_3_count": "81855"}, "KALIMANTAN TENGAH": {"cakupan_ratio": "69.14", "paslon_1_count": "149991", "paslon_2_count": "625904", "paslon_3_count": "93617"}, "KALIMANTAN TIMUR": {"cakupan_ratio": "62.54", "paslon_1_count": "196575", "paslon_2_count": "656092", "paslon_3_count": "101523"}, "KALIMANTAN UTARA": {"cakupan_ratio": "66.54", "paslon_1_count": "44736", "paslon_2_count": "167655", "paslon_3_count": "29471"}, "KEPULAUAN BANGKA BELITUNG": {"cakupan_ratio": "81.0", "paslon_1_count": "140272", "paslon_2_count": "380564", "paslon_3_count": "112730"}, "KEPULAUAN RIAU": {"cakupan_ratio": "55.41", "paslon_1_count": "195789", "paslon_2_count": "333590", "paslon_3_count": "69497"}, "LAMPUNG": {"cakupan_ratio": "85.68", "paslon_1_count": "587497", "paslon_2_count": "2726886", "paslon_3_count": "598745"}, "MALUKU": {"cakupan_ratio": "50.36", "paslon_1_count": "92748", "paslon_2_count": "318182", "paslon_3_count": "83877"}, "MALUKU UTARA": {"cakupan_ratio": "52.86", "paslon_1_count": "109573", "paslon_2_count": "248689", "paslon_3_count": "50809"}, "NUSA TENGGARA BARAT": {"cakupan_ratio": "76.71", "paslon_1_count": "544580", "paslon_2_count": "1435535", "paslon_3_count": "166498"}, "NUSA TENGGARA TIMUR": {"cakupan_ratio": "65.85", "paslon_1_count": "71211", "paslon_2_count": "790993", "paslon_3_count": "428138"}, "P A P U A": {"cakupan_ratio": "27.92", "paslon_1_count": "9018", "paslon_2_count": "50456", "paslon_3_count": "24206"}, "PAPUA BARAT": {"cakupan_ratio": "23.66", "paslon_1_count": "6731", "paslon_2_count": "37422", "paslon_3_count": "16728"}, "PAPUA BARAT DAYA": {"cakupan_ratio": "36.97", "paslon_1_count": "9519", "paslon_2_count": "41445", "paslon_3_count": "18929"}, "PAPUA PEGUNUNGAN": {"cakupan_ratio": "0.07", "paslon_1_count": "145", "paslon_2_count": "207", "paslon_3_count": "141"}, "PAPUA SELATAN": {"cakupan_ratio": "17.97", "paslon_1_count": "2671", "paslon_2_count": "19665", "paslon_3_count": "4901"}, "PAPUA TENGAH": {"cakupan_ratio": "4.64", "paslon_1_count": "4773", "paslon_2_count": "27722", "paslon_3_count": "12783"}, "RIAU": {"cakupan_ratio": "62.43", "paslon_1_count": "773583", "paslon_2_count": "1034113", "paslon_3_count": "188822"}, "SULAWESI BARAT": {"cakupan_ratio": "82.53", "paslon_1_count": "172298", "paslon_2_count": "395667", "paslon_3_count": "45267"}, "SULAWESI SELATAN": {"cakupan_ratio": "75.52", "paslon_1_count": "1521945", "paslon_2_count": "2263719", "paslon_3_count": "196365"}, "SULAWESI TENGAH": {"cakupan_ratio": "72.04", "paslon_1_count": "263561", "paslon_2_count": "828697", "paslon_3_count": "107044"}, "SULAWESI TENGGARA": {"cakupan_ratio": "80.51", "paslon_1_count": "224911", "paslon_2_count": "670672", "paslon_3_count": "55832"}, "SULAWESI UTARA": {"cakupan_ratio": "87.05", "paslon_1_count": "103070", "paslon_2_count": "1058159", "paslon_3_count": "245351"}, "SUMATERA BARAT": {"cakupan_ratio": "75.17", "paslon_1_count": "986724", "paslon_2_count": "679866", "paslon_3_count": "71948"}, "SUMATERA SELATAN": {"cakupan_ratio": "77.36", "paslon_1_count": "567736", "paslon_2_count": "2166496", "paslon_3_count": "365454"}, "SUMATERA UTARA": {"cakupan_ratio": "57.28", "paslon_1_count": "839354", "paslon_2_count": "1757688", "paslon_3_count": "362977"}, "Luar Negeri55.48%": {"cakupan_ratio": "0.0", "paslon_1_count": "82685", "paslon_2_count": "197676", "paslon_3_count": "73667"}}, "timestamp": 1708429818.849996}